{
  "entries": [
    "components/select/bq-select.js",
    "components/accordion/bq-accordion.js",
    "components/accordion-group/bq-accordion-group.js",
    "components/alert/bq-alert.js",
    "components/avatar/bq-avatar.js",
    "components/badge/bq-badge.js",
    "components/breadcrumb/bq-breadcrumb.js",
    "components/breadcrumb-item/bq-breadcrumb-item.js",
    "components/button/bq-button.js",
    "components/card/bq-card.js",
    "components/checkbox/bq-checkbox.js",
    "components/col/bq-col.js",
    "components/date-picker/bq-date-picker.js",
    "components/dialog/bq-dialog.js",
    "components/divider/bq-divider.js",
    "components/drawer/bq-drawer.js",
    "components/dropdown/bq-dropdown.js",
    "components/empty-state/bq-empty-state.js",
    "components/grid/bq-grid.js",
    "components/icon/bq-icon.js",
    "components/input/bq-input.js",
    "components/logo/bq-logo.js",
    "components/notification/bq-notification.js",
    "components/option/bq-option.js",
    "components/option-group/bq-option-group.js",
    "components/option-list/bq-option-list.js",
    "components/page-title/bq-page-title.js",
    "components/panel/bq-panel.js",
    "components/progress/bq-progress.js",
    "components/radio/bq-radio.js",
    "components/radio-group/bq-radio-group.js",
    "components/row/bq-row.js",
    "components/side-menu/bq-side-menu.js",
    "components/side-menu-item/bq-side-menu-item.js",
    "components/slider/bq-slider.js",
    "components/spinner/bq-spinner.js",
    "components/status/bq-status.js",
    "components/step-item/bq-step-item.js",
    "components/steps/bq-steps.js",
    "components/switch/bq-switch.js",
    "components/tab/bq-tab.js",
    "components/tab-group/bq-tab-group.js",
    "components/tag/bq-tag.js",
    "components/text/bq-text.js",
    "components/textarea/bq-textarea.js",
    "components/toast/bq-toast.js",
    "components/tooltip/bq-tooltip.js"
  ],
  "compiler": {
    "name": "@stencil/core",
    "version": "4.23.2",
    "typescriptVersion": "5.5.4"
  },
  "collections": [],
  "bundles": []
}